von/__about__.py
von/__init__.py
von/__main__.py
von/api.py
von/clipboard.py
von/fzf.py
von/model.py
von/puid.py
von/rc.py
von/strparse.py
von/term.py
von/termcolors.py
von/view.py
von/controller/__init__.py
von/controller/add.py
von/controller/asy.py
von/controller/br.py
von/controller/cd.py
von/controller/clear.py
von/controller/edit.py
von/controller/fixnames.py
von/controller/index.py
von/controller/link.py
von/controller/markup.py
von/controller/paths.py
von/controller/po.py
von/controller/preview.py
von/controller/search.py
von/controller/show.py
von/controller/solve.py
von/controller/status.py
vondb-3.6.0.dist-info/METADATA
vondb-3.6.0.dist-info/WHEEL
vondb-3.6.0.dist-info/entry_points.txt
vondb-3.6.0.dist-info/licenses/LICENSE
vondb-3.6.0.dist-info/RECORD
