Metadata-Version: 2.4
Name: vondb
Version: 3.6.0
Summary: VON: vEnhance's Olympiad Navigator
Project-URL: repository, https://github.com/vEnhance/von/
Author-email: Evan Chen <evan@evanchen.cc>
License: MPL-2.0
License-File: LICENSE
Requires-Python: <4.0,>=3.10
Requires-Dist: colorama>=0.4.3; sys_platform == 'win32'
Requires-Dist: pyperclip>=1.9.0
Requires-Dist: pyreadline3>=3.0.6; sys_platform == 'win32'
Requires-Dist: pyyaml>=6.0.2
